odoo9_addon_sale_procurement_group_by_requested_date-9.0.1.0.0-py2.7-nspkg.pth
odoo9_addon_sale_procurement_group_by_requested_date-9.0.1.0.0.dist-info/DESCRIPTION.rst
odoo9_addon_sale_procurement_group_by_requested_date-9.0.1.0.0.dist-info/METADATA
odoo9_addon_sale_procurement_group_by_requested_date-9.0.1.0.0.dist-info/RECORD
odoo9_addon_sale_procurement_group_by_requested_date-9.0.1.0.0.dist-info/WHEEL
odoo9_addon_sale_procurement_group_by_requested_date-9.0.1.0.0.dist-info/metadata.json
odoo9_addon_sale_procurement_group_by_requested_date-9.0.1.0.0.dist-info/namespace_packages.txt
odoo9_addon_sale_procurement_group_by_requested_date-9.0.1.0.0.dist-info/top_level.txt
odoo_addons/sale_procurement_group_by_requested_date/README.rst
odoo_addons/sale_procurement_group_by_requested_date/__init__.py
odoo_addons/sale_procurement_group_by_requested_date/__openerp__.py
odoo_addons/sale_procurement_group_by_requested_date/models/__init__.py
odoo_addons/sale_procurement_group_by_requested_date/models/sale_order.py
odoo_addons/sale_procurement_group_by_requested_date/tests/__init__.py
odoo_addons/sale_procurement_group_by_requested_date/tests/test_sale_procurement_group_by_requested_date.py
